aiograpi_fixed/__init__.py
aiograpi_fixed/config.py
aiograpi_fixed/exceptions.py
aiograpi_fixed/extractors.py
aiograpi_fixed/reqwests.py
aiograpi_fixed/story.py
aiograpi_fixed/types.py
aiograpi_fixed/utils.py
aiograpi_fixed/zones.py
aiograpi_fixed/mixins/__init__.py
aiograpi_fixed/mixins/account.py
aiograpi_fixed/mixins/album.py
aiograpi_fixed/mixins/auth.py
aiograpi_fixed/mixins/bloks.py
aiograpi_fixed/mixins/challenge.py
aiograpi_fixed/mixins/clip.py
aiograpi_fixed/mixins/collection.py
aiograpi_fixed/mixins/comment.py
aiograpi_fixed/mixins/direct.py
aiograpi_fixed/mixins/fbsearch.py
aiograpi_fixed/mixins/graphql.py
aiograpi_fixed/mixins/hashtag.py
aiograpi_fixed/mixins/highlight.py
aiograpi_fixed/mixins/igtv.py
aiograpi_fixed/mixins/insights.py
aiograpi_fixed/mixins/location.py
aiograpi_fixed/mixins/media.py
aiograpi_fixed/mixins/multiple_accounts.py
aiograpi_fixed/mixins/note.py
aiograpi_fixed/mixins/notification.py
aiograpi_fixed/mixins/password.py
aiograpi_fixed/mixins/photo.py
aiograpi_fixed/mixins/private.py
aiograpi_fixed/mixins/public.py
aiograpi_fixed/mixins/share.py
aiograpi_fixed/mixins/signup.py
aiograpi_fixed/mixins/story.py
aiograpi_fixed/mixins/timeline.py
aiograpi_fixed/mixins/totp.py
aiograpi_fixed/mixins/track.py
aiograpi_fixed/mixins/user.py
aiograpi_fixed/mixins/video.py
aiograpi_fixed-0.5.0.dist-info/METADATA
aiograpi_fixed-0.5.0.dist-info/WHEEL
aiograpi_fixed-0.5.0.dist-info/top_level.txt
aiograpi_fixed-0.5.0.dist-info/RECORD
