Metadata-Version: 2.4
Name: aiograpi-fixed
Version: 0.5.0
Summary: Working version of aiograpi (Asynchronous Instagram Private API wrapper)
Requires-Python: >=3.11
Requires-Dist: pydantic==2.11.5
Requires-Dist: moviepy==1.0.3
Requires-Dist: httpx==0.28.1
Requires-Dist: pillow==12.1.0
Requires-Dist: orjson==3.10.18
Requires-Dist: zstandard==0.23.0
Requires-Dist: pycryptodomex==3.23.0
